LICENSE
MANIFEST.in
README.md
setup.py
bin/thingscoop
thingscoop/__init__.py
thingscoop/classifier.py
thingscoop/models.py
thingscoop/preview.py
thingscoop/query.py
thingscoop/search.py
thingscoop/utils.py
thingscoop.egg-info/PKG-INFO
thingscoop.egg-info/SOURCES.txt
thingscoop.egg-info/dependency_links.txt
thingscoop.egg-info/pbr.json
thingscoop.egg-info/requires.txt
thingscoop.egg-info/top_level.txt