Metadata-Version: 1.0
Name: thingscoop
Version: 0.1
Summary: Command-line utility for searching and filtering videos based on objects that appear in them using convolutional neural networks
Home-page: https://github.com/agermanidis/thingscoop
Author: Anastasis Germanidis
Author-email: agermanidis@gmail.com
License: MIT
Platform: UNKNOWN
